Workbook

Sheet Cover
A1: SEA LIMITED (NYSE: SE)
A2: Three-Statement Integrated Financial Model | FY2021A–FY2026F
A5: MODEL OVERVIEW
A6: Company | B6: Sea Limited
A7: Ticker | B7: NYSE: SE
A8: Currency | B8: USD Millions
A9: Fiscal Year End | B9: December 31
A10: Historical Data | B10: FY2021A – FY2024A (Approximate; verify from 20-F)
A11: Projection Period | B11: FY2025F – FY2026F (Assumptions-driven)
A12: Model Built | B12: Q2 2026
A13: Analyst | B13: Aung Khant Zaw
A16: WORKSHEET NAVIGATION
A17: Assumptions | B17: All model inputs and assumptions
A18: Income Statement | B18: P&L: Revenue → Gross Profit → EBITDA → Net Income
A19: Balance Sheet | B19: Assets, Liabilities & Stockholders' Equity
A20: Cash Flow | B20: Operating / Investing / Financing + FCF
A21: KPI Dashboard | B21: Summary metrics, margins, ratios across all years
A24: COLOR KEY
A25: Blue text | B25: Hardcoded historical inputs – verify from source filings
A26: Black text | B26: Formulas calculated within the same sheet
A27: Green text | B27: Formulas linking across sheets (e.g., IS → CFS)
A28: Yellow bg | B28: Key assumptions requiring attention or update
A31: DISCLAIMER: All historical financial data are approximate figures sourced from Sea Limited 20-F Annual Reports. Users must verify all figures from official SEC EDGAR filings before use in any investment decision. This model is built for educational and portfolio demonstration purposes only.

Sheet Assumptions
A1: SEA LIMITED (SE) — MODEL ASSUMPTIONS
A2: Category | B2: Assumption | C2: FY2025F | D2: FY2026F | E2: Notes
A3: Color Key: Blue = Hardcoded Input | Black = Formula | Green = Cross-sheet Link
A5: REVENUE ASSUMPTIONS
A6: Revenue | B6: Garena (Digital Entertainment) Growth | C6: -0.1 | D6: -0.1 | E6: Continued user decline; Free Fire maturing
A7: Revenue | B7: Shopee (E-Commerce) Growth | C7: 0.2 | D7: 0.15 | E7: Strong SEA e-comm penetration continues
A8: Revenue | B8: SeaMoney (Digital Fin Services) Growth | C8: 0.25 | D8: 0.2 | E8: Fintech scaling; SPayLater & insurance growth
A10: INCOME STATEMENT MARGIN ASSUMPTIONS
A11: Margins | B11: Cost of Revenue (% of Revenue) | C11: 0.61 | D11: 0.6 | E11: Slight improvement as Shopee scales
A12: Margins | B12: Sales & Marketing (% of Revenue) | C12: 0.11 | D12: 0.105 | E12: Marketing efficiency gains
A13: Margins | B13: Research & Development (% of Revenue) | C13: 0.065 | D13: 0.06 | E13: R&D leverage on larger revenue base
A14: Margins | B14: General & Administrative (% of Revenue) | C14: 0.038 | D14: 0.035 | E14: G&A leverage
A15: Margins | B15: Depreciation & Amortization (% of Rev) | C15: 0.033 | D15: 0.03 | E15: Asset base stabilizing
A17: BELOW-THE-LINE ASSUMPTIONS
A18: Below Line | B18: Interest Income (% of avg. Cash) | C18: 0.04 | D18: 0.04 | E18: Treasury yield assumption
A19: Below Line | B19: Interest Expense (% of avg. LT Debt) | C19: 0.07 | D19: 0.07 | E19: Weighted avg cost of debt
A20: Below Line | B20: Other Income/(Expense) – USD mm | C20: 50 | D20: 60 | E20: Forex gains, misc income
A21: Below Line | B21: Effective Tax Rate | C21: 0.08 | D21: 0.09 | E21: Low rate – regional tax exemptions
A23: BALANCE SHEET ASSUMPTIONS
A24: Working Capital | B24: Days Sales Outstanding (DSO) – days | C24: 17 | D24: 16 | E24: AR collection; fast digital payments
A25: Working Capital | B25: Days Inventory Outstanding (DIO) – days | C25: 10 | D25: 9 | E25: Low inventory (mainly Shopee Mall)
A26: Working Capital | B26: Days Payable Outstanding (DPO) – days | C26: 43 | D26: 43 | E26: Seller payment terms
A27: CapEx | B27: Capital Expenditure (% of Revenue) | C27: 0.035 | D27: 0.032 | E27: Servers, logistics, offices
A28: Financing | B28: LT Debt Repayment – USD mm (annual) | C28: 300 | D28: 300 | E28: Scheduled principal repayments
A29: Financing | B29: Stock-Based Compensation – USD mm (annual) | C29: 550 | D29: 500 | E29: SBC cash add-back in CFS
A30: Financing | B30: APIC Increase from SBC – USD mm (annual) | C30: 550 | D30: 500 | E30: Offsets SBC expense in equity
A32: REFERENCE DATA
A33: Reference | B33: Diluted Shares Outstanding – mm | C33: 585 | D33: 590 | E33: Approximate; verify from 20-F
A34: Reference | B34: WACC (for DCF reference only) | C34: 0.11 | D34: 0.11 | E34: 10-12% range; verify with CAPM
A37: ⚠ All historical figures are approximate – please verify from Sea Limited 20-F Annual Reports (SEC EDGAR: https://www.sec.gov/cgi-bin/browse-edgar?action=getcompany&CIK=SE)

Sheet Income Statement
A1: SEA LIMITED (NYSE: SE) — INCOME STATEMENT | USD Millions
C2: FY2021A | D2: FY2022A | E2: FY2023A | F2: FY2024A | G2: FY2025F | H2: FY2026F
A3: (USD millions, except per share data)
A5: REVENUE
A6: Digital Entertainment (Garena) | C6: 4322 | D6: 2277 | E6: 1780 | F6: 1590 | G6: =F6*(1+Assumptions!C6) -> 1431 | H6: =G6*(1+Assumptions!D6) -> 1287.9
A7: E-Commerce (Shopee) | C7: 5126 | D7: 8551 | E7: 9069 | F7: 12044 | G7: =F7*(1+Assumptions!C7) -> 14452.8 | H7: =G7*(1+Assumptions!D7) -> 16620.72
A8: Digital Financial Services (SeaMoney) | C8: 499 | D8: 1621 | E8: 2286 | F8: 2384 | G8: =F8*(1+Assumptions!C8) -> 2980 | H8: =G8*(1+Assumptions!D8) -> 3576
A9: Total Revenue | C9: 9947 | D9: 12449 | E9: 13135 | F9: 16018 | G9: =SUM(G6:G8) -> 18863.8 | H9: =SUM(H6:H8) -> 21484.62
A10: COST & GROSS PROFIT
A11: Cost of Revenue | C11: 6252 | D11: 7474 | E11: 8135 | F11: 9771 | G11: =G9*Assumptions!C11 -> 11506.918 | H11: =H9*Assumptions!D11 -> 12890.772
A12: Gross Profit | C12: =C9-C11 -> 3695 | D12: =D9-D11 -> 4975 | E12: =E9-E11 -> 5000 | F12: =F9-F11 -> 6247 | G12: =G9-G11 -> 7356.882 | H12: =H9-H11 -> 8593.848
A13: Gross Margin % | C13: =IFERROR(C12/C9,"-") -> 0.37146878 | D13: =IFERROR(D12/D9,"-") -> 0.39963049 | E13: =IFERROR(E12/E9,"-") -> 0.38066235 | F13: =IFERROR(F12/F9,"-") -> 0.38999875 | G13: =IFERROR(G12/G9,"-") -> 0.39 | H13: =IFERROR(H12/H9,"-") -> 0.4
A15: OPERATING EXPENSES
A16: Sales & Marketing | C16: 4426 | D16: 2901 | E16: 1488 | F16: 1762 | G16: =G9*Assumptions!C14 -> 716.8244 | H16: =H9*Assumptions!D14 -> 751.9617
A17: Research & Development | C17: 855 | D17: 929 | E17: 893 | F17: 1041 | G17: =G9*Assumptions!C15 -> 622.5054 | H17: =H9*Assumptions!D15 -> 644.5386
A18: General & Administrative | C18: 482 | D18: 517 | E18: 502 | F18: 602 | G18: =G9*Assumptions!C14 -> 716.8244 | H18: =H9*Assumptions!D14 -> 751.9617
A19: Total Operating Expenses | C19: =SUM(C16:C18) -> 5763 | D19: =SUM(D16:D18) -> 4347 | E19: =SUM(E16:E18) -> 2883 | F19: =SUM(F16:F18) -> 3405 | G19: =SUM(G16:G18) -> 2056.1542 | H19: =SUM(H16:H18) -> 2148.462
A20: PROFITABILITY
A21: EBITDA | C21: =C12-C19+C23 -> -1588 | D21: =D12-D19+D23 -> 1148 | E21: =E12-E19+E23 -> 2607 | F21: =F12-F19+F23 -> 3392 | G21: =G12-G19+G23 -> 5923.2332 | H21: =H12-H19+H23 -> 7089.9246
A22: EBITDA Margin % | C22: =IFERROR(C21/C9,"-") -> -0.15964612 | D22: =IFERROR(D21/D9,"-") -> 0.092216242 | E22: =IFERROR(E21/E9,"-") -> 0.19847735 | F22: =IFERROR(F21/F9,"-") -> 0.21176177 | G22: =IFERROR(G21/G9,"-") -> 0.314 | H22: =IFERROR(H21/H9,"-") -> 0.33
A23: Depreciation & Amortization | C23: 480 | D23: 520 | E23: 490 | F23: 550 | G23: =G9*Assumptions!C15 -> 622.5054 | H23: =H9*Assumptions!D15 -> 644.5386
A24: EBIT (Operating Income) | C24: =C12-C19 -> -2068 | D24: =D12-D19 -> 628 | E24: =E12-E19 -> 2117 | F24: =F12-F19 -> 2842 | G24: =G12-G19 -> 5300.7278 | H24: =H12-H19 -> 6445.386
A25: EBIT Margin % | C25: =IFERROR(C24/C9,"-") -> -0.20790188 | D25: =IFERROR(D24/D9,"-") -> 0.050445819 | E25: =IFERROR(E24/E9,"-") -> 0.16117244 | F25: =IFERROR(F24/F9,"-") -> 0.1774254 | G25: =IFERROR(G24/G9,"-") -> 0.281 | H25: =IFERROR(H24/H9,"-") -> 0.3
A27: BELOW THE LINE
A28: Interest Income | C28: 120 | D28: 162 | E28: 245 | F28: 380 | G28: =('Balance Sheet'!F8+'Balance Sheet'!G8)/2*Assumptions!C18 -> 32.571759 | H28: =('Balance Sheet'!G8+'Balance Sheet'!H8)/2*Assumptions!D18 -> 36.40759
A29: Interest Expense | C29: -282 | D29: -296 | E29: -258 | F29: -238 | G29: =-('Balance Sheet'!F31+'Balance Sheet'!G31)/2*Assumptions!C19 -> -192.185 | H29: =-('Balance Sheet'!G31+'Balance Sheet'!H31)/2*Assumptions!D19 -> -170.56445
A30: Other Income/(Expense), net | C30: -48 | D30: 22 | E30: -18 | F30: 45 | G30: =Assumptions!C20 -> 50 | H30: =Assumptions!D20 -> 60
A31: Earnings Before Tax (EBT) | C31: =C24+C28+C29+C30 -> -2278 | D31: =D24+D28+D29+D30 -> 516 | E31: =E24+E28+E29+E30 -> 2086 | F31: =F24+F28+F29+F30 -> 3029 | G31: =G24+G28+G29+G30 -> 5191.1146 | H31: =H24+H28+H29+H30 -> 6371.2291
A32: Income Tax Expense | C32: 72 | D32: 96 | E32: 151 | F32: 245 | G32: =MAX(G31*Assumptions!C21,0) -> 415.28916 | H32: =MAX(H31*Assumptions!D21,0) -> 573.41062
A33: Net Income (Loss) | C33: =C31-C32 -> -2350 | D33: =D31-D32 -> 420 | E33: =E31-E32 -> 1935 | F33: =F31-F32 -> 2784 | G33: =G31-G32 -> 4775.8254 | H33: =H31-H32 -> 5797.8185
A34: Net Margin % | C34: =IFERROR(C33/C9,"-") -> -0.23625214 | D34: =IFERROR(D33/D9,"-") -> 0.03373765 | E34: =IFERROR(E33/E9,"-") -> 0.14731633 | F34: =IFERROR(F33/F9,"-") -> 0.17380447 | G34: =IFERROR(G33/G9,"-") -> 0.25317409 | H34: =IFERROR(H33/H9,"-") -> 0.26985902
A36: PER SHARE DATA
A37: Diluted Shares Outstanding (mm) | C37: 575 | D37: 577 | E37: 580 | F37: 582 | G37: =Assumptions!C33 -> 585 | H37: =Assumptions!D33 -> 590
A38: Earnings Per Share (diluted) – USD | C38: =IFERROR(C33/C37,"-") -> -4.0869565 | D38: =IFERROR(D33/D37,"-") -> 0.72790295 | E38: =IFERROR(E33/E37,"-") -> 3.3362069 | F38: =IFERROR(F33/F37,"-") -> 4.7835052 | G38: =IFERROR(G33/G37,"-") -> 8.1638041 | H38: =IFERROR(H33/H37,"-") -> 9.826811
A40: Source: Sea Limited 20-F Annual Reports (approximate – verify exact figures from SEC EDGAR)

Sheet Balance Sheet
A1: SEA LIMITED (NYSE: SE) — BALANCE SHEET | USD Millions
C2: FY2021A | D2: FY2022A | E2: FY2023A | F2: FY2024A | G2: FY2025F | H2: FY2026F
A3: (USD millions)
A5: ASSETS
A6: Cash & Cash Equivalents | C6: 7200 | D6: 6000 | E6: 7200 | F6: 9100 | G6: ='Cash Flow'!G28 -> 14029.861 | H6: ='Cash Flow'!H28 -> 19981.94
A7: Restricted Cash | C7: 1100 | D7: 1050 | E7: 980 | F7: 1050 | G7: =F7 -> 1050 | H7: =G7 -> 1050
A8: Accounts Receivable, net | C8: 485 | D8: 580 | E8: 620 | F8: 750 | G8: ='Income Statement'!G9/365*Assumptions!C24 -> 878.58795 | H8: ='Income Statement'!H9/365*Assumptions!D24 -> 941.79156
A9: Inventories | C9: 315 | D9: 250 | E9: 230 | F9: 280 | G9: ='Income Statement'!G11/365*Assumptions!C25 -> 315.25803 | H9: ='Income Statement'!H11/365*Assumptions!D25 -> 317.85465
A10: Other Current Assets | C10: 900 | D10: 1100 | E10: 1200 | F10: 1400 | G10: ='Income Statement'!G9*0.087 -> 1641.1506 | H10: ='Income Statement'!H9*0.087 -> 1869.1619
A11: Total Current Assets | C11: =SUM(C6:C10) -> 10000 | D11: =SUM(D6:D10) -> 8980 | E11: =SUM(E6:E10) -> 10230 | F11: =SUM(F6:F10) -> 12580 | G11: =SUM(G6:G10) -> 17914.858 | H11: =SUM(H6:H10) -> 24160.748
A13: NON-CURRENT ASSETS
A14: Property & Equipment, net | C14: 950 | D14: 850 | E14: 790 | F14: 900 | G14: =F14+'Income Statement'!G9*Assumptions!C27-'Income Statement'!G23 -> 937.7276 | H14: =G14+'Income Statement'!H9*Assumptions!D27-'Income Statement'!H23 -> 980.69684
A15: Intangibles & Goodwill | C15: 450 | D15: 425 | E15: 410 | F15: 420 | G15: =F15 -> 420 | H15: =G15 -> 420
A16: Other Non-Current Assets | C16: 1300 | D16: 1245 | E16: 1380 | F16: 1450 | G16: ='Income Statement'!G9*0.09 -> 1697.742 | H16: ='Income Statement'!H9*0.09 -> 1933.6158
A17: Total Non-Current Assets | C17: =SUM(C14:C16) -> 2700 | D17: =SUM(D14:D16) -> 2520 | E17: =SUM(E14:E16) -> 2580 | F17: =SUM(F14:F16) -> 2770 | G17: =SUM(G14:G16) -> 3055.4696 | H17: =SUM(H14:H16) -> 3334.3126
A19: TOTAL ASSETS | C19: =C11+C17 -> 12700 | D19: =D11+D17 -> 11500 | E19: =E11+E17 -> 12810 | F19: =F11+F17 -> 15350 | G19: =G11+G17 -> 20970.328 | H19: =H11+H17 -> 27495.061
A21: LIABILITIES
A22: Accounts Payable | C22: 700 | D22: 880 | E22: 950 | F22: 1150 | G22: ='Income Statement'!G11/365*Assumptions!C26 -> 1355.6095 | H22: ='Income Statement'!H11/365*Assumptions!D26 -> 1518.6389
A23: Accrued Expenses & Other | C23: 1450 | D23: 1350 | E23: 1400 | F23: 1600 | G23: ='Income Statement'!G9*0.1 -> 1886.38 | H23: ='Income Statement'!H9*0.1 -> 2148.462
A24: Deferred Revenue | C24: 240 | D24: 210 | E24: 200 | F24: 220 | G24: =F24*0.97 -> 213.4 | H24: =G24*0.97 -> 206.998
A25: Short-term Borrowings | C25: 850 | D25: 800 | E25: 750 | F25: 700 | G25: =F25-50 -> 650 | H25: =G25-50 -> 600
A26: Total Current Liabilities | C26: =SUM(C22:C25) -> 3240 | D26: =SUM(D22:D25) -> 3240 | E26: =SUM(E22:E25) -> 3300 | F26: =SUM(F22:F25) -> 3670 | G26: =SUM(G22:G25) -> 4105.3895 | H26: =SUM(H22:H25) -> 4474.0989
A28: NON-CURRENT LIABILITIES
A29: Long-term Debt | C29: 3500 | D29: 3200 | E29: 2900 | F29: 2600 | G29: =F29-Assumptions!C28 -> 2300 | H29: =G29-Assumptions!D28 -> 2000
A30: Other Non-Current Liabilities | C30: 380 | D30: 350 | E30: 330 | F30: 300 | G30: =F30*0.97 -> 291 | H30: =G30*0.97 -> 282.27
A31: Total Non-Current Liabilities | C31: =SUM(C29:C30) -> 3880 | D31: =SUM(D29:D30) -> 3550 | E31: =SUM(E29:E30) -> 3230 | F31: =SUM(F29:F30) -> 2900 | G31: =SUM(G29:G30) -> 2591 | H31: =SUM(H29:H30) -> 2282.27
A33: TOTAL LIABILITIES | C33: =C26+C31 -> 7120 | D33: =D26+D31 -> 6790 | E33: =E26+E31 -> 6530 | F33: =F26+F31 -> 6570 | G33: =G26+G31 -> 6696.3895 | H33: =H26+H31 -> 6756.3689
A35: STOCKHOLDERS' EQUITY
A36: Common Stock & Additional Paid-In Capital | C36: 7850 | D36: 8250 | E36: 8600 | F36: 9000 | G36: =F36+Assumptions!C30 -> 9550 | H36: =G36+Assumptions!D30 -> 10050
A37: Retained Earnings (Accumulated Deficit) | C37: -2270 | D37: -3540 | E37: -2320 | F37: -220 | G37: =F37+'Income Statement'!G33 -> 4555.8254 | H37: =G37+'Income Statement'!H33 -> 10353.644
A38: Total Stockholders' Equity | C38: =C36+C37 -> 5580 | D38: =D36+D37 -> 4710 | E38: =E36+E37 -> 6280 | F38: =F36+F37 -> 8780 | G38: =G36+G37 -> 14105.825 | H38: =H36+H37 -> 20403.644
A40: TOTAL LIABILITIES & EQUITY | C40: =C33+C38 -> 12700 | D40: =D33+D38 -> 11500 | E40: =E33+E38 -> 12810 | F40: =F33+F38 -> 15350 | G40: =G33+G38 -> 20802.215 | H40: =H33+H38 -> 27160.013
A42: Balance Check (Assets – L&E) → Must = 0 for projection years | C42: =C19-C40 -> 0 | D42: =D19-D40 -> 0 | E42: =E19-E40 -> 0 | F42: =F19-F40 -> 0 | G42: =G19-G40 -> 168.1126 | H42: =H19-H40 -> 335.04774
A44: Source: Sea Limited 20-F Annual Reports (approximate – verify exact figures from SEC EDGAR)

Sheet Cash Flow
A1: SEA LIMITED (NYSE: SE) — CASH FLOW STATEMENT | USD Millions
C2: FY2021A | D2: FY2022A | E2: FY2023A | F2: FY2024A | G2: FY2025F | H2: FY2026F
A3: (USD millions)
A5: OPERATING ACTIVITIES
A6: Net Income (Loss) | C6: -2350 | D6: 420 | E6: 1806 | F6: 2784 | G6: ='Income Statement'!G33 -> 4775.8254 | H6: ='Income Statement'!H33 -> 5797.8185
A7: Add: Depreciation & Amortization | C7: 480 | D7: 520 | E7: 490 | F7: 550 | G7: ='Income Statement'!G23 -> 622.5054 | H7: ='Income Statement'!H23 -> 644.5386
A8: Add: Stock-Based Compensation (non-cash) | C8: 650 | D8: 700 | E8: 530 | F8: 580 | G8: =Assumptions!C29 -> 550 | H8: =Assumptions!D29 -> 500
A9: (Increase)/Decrease in Accounts Receivable | C9: -120 | D9: -95 | E9: -40 | F9: -130 | G9: =-('Balance Sheet'!G8-'Balance Sheet'!F8) -> -128.58795 | H9: =-('Balance Sheet'!H8-'Balance Sheet'!G8) -> -63.203616
A10: (Increase)/Decrease in Inventories | C10: -85 | D10: 65 | E10: 20 | F10: -50 | G10: =-('Balance Sheet'!G9-'Balance Sheet'!F9) -> -35.258027 | H10: =-('Balance Sheet'!H9-'Balance Sheet'!G9) -> -2.5966247
A11: Increase/(Decrease) in Accounts Payable | C11: 200 | D11: 180 | E11: 70 | F11: 200 | G11: ='Balance Sheet'!G22-'Balance Sheet'!F22 -> 205.60952 | H11: ='Balance Sheet'!H22-'Balance Sheet'!G22 -> 163.02938
A12: Changes in Other Working Capital & Other | C12: -175 | D12: -70 | E12: -5 | F12: -4 | G12: 0 | H12: 0
A13: Net Cash from Operating Activities | C13: -1400 | D13: 1720 | E13: 2871 | F13: 3930 | G13: =SUM(G6:G12) -> 5990.0943 | H13: =SUM(H6:H12) -> 7039.5863
A15: INVESTING ACTIVITIES
A16: Capital Expenditures | C16: -410 | D16: -420 | E16: -430 | F16: -560 | G16: =-'Income Statement'!G9*Assumptions!C27 -> -660.233 | H16: =-'Income Statement'!H9*Assumptions!D27 -> -687.50784
A17: Acquisitions & Investments, net | C17: -1290 | D17: -480 | E17: -330 | F17: -290 | G17: -200 | H17: -200
A18: Net Cash from Investing Activities | C18: -1700 | D18: -900 | E18: -760 | F18: -850 | G18: =SUM(G16:G17) -> -860.233 | H18: =SUM(H16:H17) -> -887.50784
A20: FINANCING ACTIVITIES
A21: Proceeds from Long-term Debt Issuance | C21: 0 | D21: 0 | E21: 0 | F21: 0 | G21: 0 | H21: 0
A22: Repayment of Long-term Debt | C22: 500 | D22: -300 | E22: -300 | F22: -300 | G22: =-Assumptions!C28 -> -300 | H22: =-Assumptions!D28 -> -300
A23: Proceeds from Stock Issuance & Other | C23: 4850 | D23: 400 | E23: 350 | F23: 400 | G23: 100 | H23: 100
A24: Net Cash from Financing Activities | C24: 4350 | D24: 100 | E24: 50 | F24: 100 | G24: =SUM(G21:G23) -> -200 | H24: =SUM(H21:H23) -> -200
A26: Net Increase/(Decrease) in Cash | C26: 2250 | D26: 920 | E26: 2161 | F26: 3180 | G26: =G13+G18+G24 -> 4929.8613 | H26: =H13+H18+H24 -> 5952.0784
A27: Beginning Cash & Cash Equivalents | C27: 2200 | D27: 7200 | E27: 6000 | F27: 7200 | G27: ='Balance Sheet'!F6 -> 9100 | H27: ='Balance Sheet'!G6 -> 14029.861
A28: Ending Cash & Cash Equivalents | C28: 7200 | D28: 6000 | E28: 7200 | F28: 9100 | G28: =G27+G26 -> 14029.861 | H28: =H27+H26 -> 19981.94
A29: FREE CASH FLOW
A30: Free Cash Flow (CFO + CapEx) | C30: -1810 | D30: 1300 | E30: 2441 | F30: 3370 | G30: =G13+G16 -> 5329.8613 | H30: =H13+H16 -> 6352.0784
A31: FCF Margin % | C31: =IFERROR(C30/'Income Statement'!C9,"-") -> -0.18196441 | D31: =IFERROR(D30/'Income Statement'!D9,"-") -> 0.10442606 | E31: =IFERROR(E30/'Income Statement'!E9,"-") -> 0.18583936 | F31: =IFERROR(F30/'Income Statement'!F9,"-") -> 0.21038831 | G31: =IFERROR(G30/'Income Statement'!G9,"-") -> 0.28254442 | H31: =IFERROR(H30/'Income Statement'!H9,"-") -> 0.29565701
A33: Source: Sea Limited 20-F Annual Reports (approximate – verify exact figures from SEC EDGAR)

Sheet KPI Dashboard
A1: SEA LIMITED (NYSE: SE) — KPI DASHBOARD | USD Millions
A2: FY2021A–FY2026F Summary | All figures in USD millions | Approximate historical data – verify from 20-F
A4: KPI | B4: FY2021A | C4: FY2022A | D4: FY2023A | E4: FY2024A | F4: FY2025F | G4: FY2026F
A6: REVENUE
A7: Revenue (USD mm) | B7: ='Income Statement'!C9 -> 9947 | C7: ='Income Statement'!D9 -> 12449 | D7: ='Income Statement'!E9 -> 13135 | E7: ='Income Statement'!F9 -> 16018 | F7: ='Income Statement'!G9 -> 18863.8 | G7: ='Income Statement'!H9 -> 21484.62
A8: YoY Revenue Growth | B8: n/m | C8: =IFERROR('Income Statement'!D9/'Income Statement'!C9-1,"n/m") -> 0.25153313 | D8: =IFERROR('Income Statement'!E9/'Income Statement'!D9-1,"n/m") -> 0.055104828 | E8: =IFERROR('Income Statement'!F9/'Income Statement'!E9-1,"n/m") -> 0.21948991 | F8: =IFERROR('Income Statement'!G9/'Income Statement'!F9-1,"n/m") -> 0.17766263 | G8: =IFERROR('Income Statement'!H9/'Income Statement'!G9-1,"n/m") -> 0.13893383
A10: PROFITABILITY
A11: Gross Profit (USD mm) | B11: ='Income Statement'!C12 -> 3695 | C11: ='Income Statement'!D12 -> 4975 | D11: ='Income Statement'!E12 -> 5000 | E11: ='Income Statement'!F12 -> 6247 | F11: ='Income Statement'!G12 -> 7356.882 | G11: ='Income Statement'!H12 -> 8593.848
A12: Gross Margin % | B12: ='Income Statement'!C13 -> 0.37146878 | C12: ='Income Statement'!D13 -> 0.39963049 | D12: ='Income Statement'!E13 -> 0.38066235 | E12: ='Income Statement'!F13 -> 0.38999875 | F12: ='Income Statement'!G13 -> 0.39 | G12: ='Income Statement'!H13 -> 0.4
A13: EBITDA (USD mm) | B13: ='Income Statement'!C21 -> -1588 | C13: ='Income Statement'!D21 -> 1148 | D13: ='Income Statement'!E21 -> 2607 | E13: ='Income Statement'!F21 -> 3392 | F13: ='Income Statement'!G21 -> 5923.2332 | G13: ='Income Statement'!H21 -> 7089.9246
A14: EBITDA Margin % | B14: ='Income Statement'!C22 -> -0.15964612 | C14: ='Income Statement'!D22 -> 0.092216242 | D14: ='Income Statement'!E22 -> 0.19847735 | E14: ='Income Statement'!F22 -> 0.21176177 | F14: ='Income Statement'!G22 -> 0.314 | G14: ='Income Statement'!H22 -> 0.33
A15: EBIT (USD mm) | B15: ='Income Statement'!C24 -> -2068 | C15: ='Income Statement'!D24 -> 628 | D15: ='Income Statement'!E24 -> 2117 | E15: ='Income Statement'!F24 -> 2842 | F15: ='Income Statement'!G24 -> 5300.7278 | G15: ='Income Statement'!H24 -> 6445.386
A16: EBIT Margin % | B16: ='Income Statement'!C25 -> -0.20790188 | C16: ='Income Statement'!D25 -> 0.050445819 | D16: ='Income Statement'!E25 -> 0.16117244 | E16: ='Income Statement'!F25 -> 0.1774254 | F16: ='Income Statement'!G25 -> 0.281 | G16: ='Income Statement'!H25 -> 0.3
A17: Net Income (USD mm) | B17: ='Income Statement'!C33 -> -2350 | C17: ='Income Statement'!D33 -> 420 | D17: ='Income Statement'!E33 -> 1935 | E17: ='Income Statement'!F33 -> 2784 | F17: ='Income Statement'!G33 -> 4775.8254 | G17: ='Income Statement'!H33 -> 5797.8185
A18: Net Margin % | B18: ='Income Statement'!C34 -> -0.23625214 | C18: ='Income Statement'!D34 -> 0.03373765 | D18: ='Income Statement'!E34 -> 0.14731633 | E18: ='Income Statement'!F34 -> 0.17380447 | F18: ='Income Statement'!G34 -> 0.25317409 | G18: ='Income Statement'!H34 -> 0.26985902
A20: CASH FLOW
A21: Free Cash Flow (USD mm) | B21: ='Cash Flow'!C30 -> -1810 | C21: ='Cash Flow'!D30 -> 1300 | D21: ='Cash Flow'!E30 -> 2441 | E21: ='Cash Flow'!F30 -> 3370 | F21: ='Cash Flow'!G30 -> 5329.8613 | G21: ='Cash Flow'!H30 -> 6352.0784
A22: FCF Margin % | B22: ='Cash Flow'!C31 -> -0.18196441 | C22: ='Cash Flow'!D31 -> 0.10442606 | D22: ='Cash Flow'!E31 -> 0.18583936 | E22: ='Cash Flow'!F31 -> 0.21038831 | F22: ='Cash Flow'!G31 -> 0.28254442 | G22: ='Cash Flow'!H31 -> 0.29565701
A23: Cash & Equivalents | B23: ='Balance Sheet'!C6 -> 7200 | C23: ='Balance Sheet'!D6 -> 6000 | D23: ='Balance Sheet'!E6 -> 7200 | E23: ='Balance Sheet'!F6 -> 9100 | F23: ='Balance Sheet'!G6 -> 14029.861 | G23: ='Balance Sheet'!H6 -> 19981.94
A25: BALANCE SHEET & LEVERAGE
A26: Total Assets (USD mm) | B26: ='Balance Sheet'!C19 -> 12700 | C26: ='Balance Sheet'!D19 -> 11500 | D26: ='Balance Sheet'!E19 -> 12810 | E26: ='Balance Sheet'!F19 -> 15350 | F26: ='Balance Sheet'!G19 -> 20970.328 | G26: ='Balance Sheet'!H19 -> 27495.061
A27: Net Debt (USD mm) | B27: =('Balance Sheet'!C29+'Balance Sheet'!C25-'Balance Sheet'!C6) -> -2850 | C27: =('Balance Sheet'!D29+'Balance Sheet'!D25-'Balance Sheet'!D6) -> -2000 | D27: =('Balance Sheet'!E29+'Balance Sheet'!E25-'Balance Sheet'!E6) -> -3550 | E27: =('Balance Sheet'!F29+'Balance Sheet'!F25-'Balance Sheet'!F6) -> -5800 | F27: =('Balance Sheet'!G29+'Balance Sheet'!G25-'Balance Sheet'!G6) -> -11079.861 | G27: =('Balance Sheet'!H29+'Balance Sheet'!H25-'Balance Sheet'!H6) -> -17381.94
A28: Current Ratio | B28: =IFERROR('Balance Sheet'!C11/'Balance Sheet'!C26,"-") -> 3.0864198 | C28: =IFERROR('Balance Sheet'!D11/'Balance Sheet'!D26,"-") -> 2.7716049 | D28: =IFERROR('Balance Sheet'!E11/'Balance Sheet'!E26,"-") -> 3.1 | E28: =IFERROR('Balance Sheet'!F11/'Balance Sheet'!F26,"-") -> 3.4277929 | F28: =IFERROR('Balance Sheet'!G11/'Balance Sheet'!G26,"-") -> 4.3637413 | G28: =IFERROR('Balance Sheet'!H11/'Balance Sheet'!H26,"-") -> 5.4001372
A29: Total Debt / Equity | B29: =IFERROR(('Balance Sheet'!C29+'Balance Sheet'!C25)/'Balance Sheet'!C38,"-") -> 0.77956989 | C29: =IFERROR(('Balance Sheet'!D29+'Balance Sheet'!D25)/'Balance Sheet'!D38,"-") -> 0.8492569 | D29: =IFERROR(('Balance Sheet'!E29+'Balance Sheet'!E25)/'Balance Sheet'!E38,"-") -> 0.58121019 | E29: =IFERROR(('Balance Sheet'!F29+'Balance Sheet'!F25)/'Balance Sheet'!F38,"-") -> 0.37585421 | F29: =IFERROR(('Balance Sheet'!G29+'Balance Sheet'!G25)/'Balance Sheet'!G38,"-") -> 0.20913345 | G29: =IFERROR(('Balance Sheet'!H29+'Balance Sheet'!H25)/'Balance Sheet'!H38,"-") -> 0.12742822
A30: Return on Equity (ROE) | B30: =IFERROR('Income Statement'!C33/'Balance Sheet'!C38,"-") -> -0.42114695 | C30: =IFERROR('Income Statement'!D33/'Balance Sheet'!D38,"-") -> 0.089171975 | D30: =IFERROR('Income Statement'!E33/'Balance Sheet'!E38,"-") -> 0.30812102 | E30: =IFERROR('Income Statement'!F33/'Balance Sheet'!F38,"-") -> 0.31708428 | F30: =IFERROR('Income Statement'!G33/'Balance Sheet'!G38,"-") -> 0.33857114 | G30: =IFERROR('Income Statement'!H33/'Balance Sheet'!H38,"-") -> 0.28415603
A32: Earnings Per Share – USD | B32: ='Income Statement'!C38 -> -4.0869565 | C32: ='Income Statement'!D38 -> 0.72790295 | D32: ='Income Statement'!E38 -> 3.3362069 | E32: ='Income Statement'!F38 -> 4.7835052 | F32: ='Income Statement'!G38 -> 8.1638041 | G32: ='Income Statement'!H38 -> 9.826811
A34: Color Key: 🔵 Blue = Hardcoded Historical Input | ⚫ Black = Formula | 🟢 Green = Cross-Sheet Link
